README.md
setup.py
youdao/__init__.py
youdao/config.py
youdao/main.py
youdao/model.py
youdao/spider.py
youdao.egg-info/PKG-INFO
youdao.egg-info/SOURCES.txt
youdao.egg-info/dependency_links.txt
youdao.egg-info/entry_points.txt
youdao.egg-info/not-zip-safe
youdao.egg-info/requires.txt
youdao.egg-info/top_level.txt
youdao/lib/CPyStarDictIndex.cpp
youdao/lib/__init__.py
youdao/lib/cpystardict.py
youdao/lib/pystardict.py