Metadata-Version: 1.1
Name: youdao
Version: 0.3.5
Summary: 基于有道API和有道词典web版的在terminal查询词的小工具,支持单词发音
Home-page: https://github.com/longcw/youdao
Author: longcw
Author-email: longch1024@gmail.com
License: MIT
Keywords: python youdao dictionary terminal
Platform: UNKNOWN
Classifier: Programming Language :: Python :: 2.7
Classifier: Programming Language :: Python :: 3
Classifier: Programming Language :: Python :: 3.2
Classifier: Programming Language :: Python :: 3.3
Classifier: Programming Language :: Python :: 3.4
Classifier: Programming Language :: Python :: 3.5
Classifier: Programming Language :: Python :: 3.6
